Metadata-Version: 2.4
Name: aplicacion_ventas_heobando
Version: 0.1.0
Summary: Paquete para gestionar ventas, precios, impuestos y descuentos
Home-page: https://github.com/heobando/aplicacion_ventas_heobando
Author: Hector Obando
Classifier: Programming Language :: Python :: 3
Classifier: License :: OSI Approved :: MIT License
Classifier: Operating System :: OS Independent
Requires-Python: >=3.6
License-File: LICENCE
Requires-Dist: setuptools
Dynamic: author
Dynamic: classifier
Dynamic: description
Dynamic: description-content-type
Dynamic: home-page
Dynamic: license-file
Dynamic: requires-dist
Dynamic: requires-python
Dynamic: summary
